imaginepy/__init__.py
imaginepy/async_imagine.py
imaginepy/constants.py
imaginepy/sync_imagine.py
imaginepy-1.1.0.dist-info/LICENSE
imaginepy-1.1.0.dist-info/METADATA
imaginepy-1.1.0.dist-info/WHEEL
imaginepy-1.1.0.dist-info/top_level.txt
imaginepy-1.1.0.dist-info/RECORD
